mobius3.py
mobius3-0.0.44.dist-info/METADATA
mobius3-0.0.44.dist-info/WHEEL
mobius3-0.0.44.dist-info/entry_points.txt
mobius3-0.0.44.dist-info/licenses/LICENSE
mobius3-0.0.44.dist-info/RECORD
