Metadata-Version: 2.4
Name: mobius3
Version: 0.0.44
Summary: Continuously and asynchronously sync a local folder to an S3 bucket
Project-URL: Source, https://github.com/uktrade/mobius3
Author-email: Department for Business and Trade <sre@digital.trade.gov.uk>
License-File: LICENSE
Classifier: License :: OSI Approved :: MIT License
Classifier: Programming Language :: Python :: 3
Requires-Python: >=3.7.0
Requires-Dist: fifolock>=0.0.20
Requires-Dist: httpx>=0.23.0
Requires-Dist: sentry-sdk>=1.11.1
Provides-Extra: dev
Requires-Dist: aiohttp==3.*; extra == 'dev'
Requires-Dist: sentry-sdk>=1.11.1; extra == 'dev'
